{
  "updatedAt": "2026-07-17T22:31:33Z",
  "companies": {
    "NVDA": {
      "status": "ready",
      "company": "NVIDIA",
      "fiscalPeriodEnd": "2026-04-30",
      "revenueTTM": 253491000000.0,
      "operatingCashflowTTM": 125648000000.0,
      "fcfTTM": 119076000000.0,
      "fcfMarginTTM": 0.4697444879699871,
      "fcfMargin3yMedian": 0.44770258129648327,
      "normalizedFcfMargin": 0.46092772530058557,
      "ttmWeight": 0.6,
      "terminalGrowth": 0.025,
      "riskFreeRate": 0.0425,
      "equityRiskPremium": 0.05,
      "rationale": "AI 数据中心利润率出现结构性抬升；保留 40% 三年中位数以避免只外推峰值。",
      "source": "Alpha Vantage INCOME_STATEMENT + CASH_FLOW（公司申报财报）"
    },
    "AAPL": {
      "status": "ready",
      "company": "Apple",
      "fiscalPeriodEnd": "2026-03-31",
      "revenueTTM": 451442000000.0,
      "operatingCashflowTTM": 140222000000.0,
      "fcfTTM": 129174000000.0,
      "fcfMarginTTM": 0.28613642505571035,
      "fcfMargin3yMedian": 0.25981710737440805,
      "normalizedFcfMargin": 0.2729767662150592,
      "ttmWeight": 0.5,
      "terminalGrowth": 0.025,
      "riskFreeRate": 0.0425,
      "equityRiskPremium": 0.05,
      "rationale": "硬件与服务组合成熟，TTM 与三年现金转化各占一半。",
      "source": "Alpha Vantage INCOME_STATEMENT + CASH_FLOW（公司申报财报）"
    },
    "MSFT": {
      "status": "ready",
      "company": "Microsoft",
      "fiscalPeriodEnd": "2026-03-31",
      "revenueTTM": 318273000000.0,
      "operatingCashflowTTM": 170141000000.0,
      "fcfTTM": 72916000000.0,
      "fcfMarginTTM": 0.22909891822429174,
      "fcfMargin3yMedian": 0.2806549795908737,
      "normalizedFcfMargin": 0.24456573663426634,
      "ttmWeight": 0.7,
      "terminalGrowth": 0.025,
      "riskFreeRate": 0.0425,
      "equityRiskPremium": 0.05,
      "rationale": "AI 基础设施资本开支已显著上升，较多采用当前现金流率。",
      "source": "Alpha Vantage INCOME_STATEMENT + CASH_FLOW（公司申报财报）"
    },
    "GOOGL": {
      "status": "ready",
      "company": "Alphabet",
      "fiscalPeriodEnd": "2026-03-31",
      "revenueTTM": 422566000000.0,
      "operatingCashflowTTM": 174353000000.0,
      "fcfTTM": 64429000000.0,
      "fcfMarginTTM": 0.1524708566235807,
      "fcfMargin3yMedian": 0.20788645155392008,
      "normalizedFcfMargin": 0.16632475535616553,
      "ttmWeight": 0.75,
      "terminalGrowth": 0.025,
      "riskFreeRate": 0.0425,
      "equityRiskPremium": 0.05,
      "rationale": "数据中心投资快速增加，当前现金流率比过去轻资本年份更具代表性。",
      "source": "Alpha Vantage INCOME_STATEMENT + CASH_FLOW（公司申报财报）"
    },
    "AMZN": {
      "status": "ready",
      "company": "Amazon",
      "fiscalPeriodEnd": "2026-03-31",
      "revenueTTM": 742776000000.0,
      "operatingCashflowTTM": 148531000000.0,
      "fcfTTM": -2472000000.0,
      "fcfMarginTTM": -0.0033280558337910756,
      "fcfMargin3yMedian": 0.05153622724971354,
      "normalizedFcfMargin": 0.010388014937085077,
      "ttmWeight": 0.75,
      "terminalGrowth": 0.025,
      "riskFreeRate": 0.0425,
      "equityRiskPremium": 0.05,
      "impliedGrowthStatus": "high_uncertainty",
      "impliedGrowthNote": "归一化自由现金流率仅为 1.0%，受大额资本开支影响，暂不将反推结果作为常规增长率展示。",
      "rationale": "AWS 与物流网络均在加大投入，当前现金转化优先。",
      "source": "Alpha Vantage INCOME_STATEMENT + CASH_FLOW（公司申报财报）"
    },
    "META": {
      "status": "ready",
      "company": "Meta",
      "fiscalPeriodEnd": "2026-03-31",
      "revenueTTM": 214963000000.0,
      "operatingCashflowTTM": 124000000000.0,
      "fcfTTM": 48253000000.0,
      "fcfMarginTTM": 0.2244711880649228,
      "fcfMargin3yMedian": 0.32502853923588976,
      "normalizedFcfMargin": 0.24961052585766452,
      "ttmWeight": 0.75,
      "terminalGrowth": 0.025,
      "riskFreeRate": 0.0425,
      "equityRiskPremium": 0.05,
      "rationale": "AI 资本开支处于高投入阶段，避免用旧年高 FCF 率高估。",
      "source": "Alpha Vantage INCOME_STATEMENT + CASH_FLOW（公司申报财报）"
    },
    "TSLA": {
      "status": "ready",
      "company": "Tesla",
      "fiscalPeriodEnd": "2026-03-31",
      "revenueTTM": 97879000000.0,
      "operatingCashflowTTM": 16528000000.0,
      "fcfTTM": 7000000000.0,
      "fcfMarginTTM": 0.07151687287365012,
      "fcfMargin3yMedian": 0.04502288861562626,
      "normalizedFcfMargin": 0.055620482318835804,
      "ttmWeight": 0.4,
      "terminalGrowth": 0.025,
      "riskFreeRate": 0.0425,
      "equityRiskPremium": 0.05,
      "rationale": "交付、库存和营运资本波动较大，以三年中位数为主。",
      "source": "Alpha Vantage INCOME_STATEMENT + CASH_FLOW（公司申报财报）"
    },
    "TSM": {
      "status": "ready",
      "company": "TSMC",
      "fiscalPeriodEnd": "2026-06-30",
      "revenueTTM": 148345953033.33334,
      "operatingCashflowTTM": 89447367533.33333,
      "fcfTTM": 39734119633.333336,
      "fcfMarginTTM": 0.2678476818602869,
      "fcfMargin3yMedian": 0.2851970594718451,
      "normalizedFcfMargin": 0.2773898395466439,
      "ttmWeight": 0.45,
      "terminalGrowth": 0.025,
      "riskFreeRate": 0.0425,
      "equityRiskPremium": 0.05,
      "reportingCurrency": "TWD",
      "modelCurrency": "USD",
      "fxRateToUsd": 0.03333333333333333,
      "rationale": "晶圆厂资本开支与景气周期显著，三年中位数为主。",
      "source": "Alpha Vantage INCOME_STATEMENT + CASH_FLOW（公司申报财报）；TSMC 金额按 1 USD = 30.0 TWD 换算"
    },
    "MU": {
      "status": "ready",
      "company": "Micron",
      "fiscalPeriodEnd": "2026-05-31",
      "revenueTTM": 90274000000.0,
      "operatingCashflowTTM": 51432000000.0,
      "fcfTTM": 27170000000.0,
      "fcfMarginTTM": 0.30097259454549485,
      "fcfMargin3yMedian": 0.004818605392059257,
      "normalizedFcfMargin": 0.10847250159576172,
      "ttmWeight": 0.35,
      "terminalGrowth": 0.025,
      "riskFreeRate": 0.0425,
      "equityRiskPremium": 0.05,
      "rationale": "存储价格周期显著，三年中位数为主以降低周期高低点影响。",
      "source": "Alpha Vantage INCOME_STATEMENT + CASH_FLOW（公司申报财报）"
    },
    "AVGO": {
      "status": "ready",
      "company": "Broadcom",
      "fiscalPeriodEnd": "2026-04-30",
      "revenueTTM": 75465000000.0,
      "operatingCashflowTTM": 33622000000.0,
      "fcfTTM": 32762000000.0,
      "fcfMarginTTM": 0.4341350294838667,
      "fcfMargin3yMedian": 0.4212750637844945,
      "normalizedFcfMargin": 0.4289910432041178,
      "ttmWeight": 0.6,
      "terminalGrowth": 0.025,
      "riskFreeRate": 0.0425,
      "equityRiskPremium": 0.05,
      "rationale": "基础设施软件整合与半导体业务并行，当前现金转化权重略高。",
      "source": "Alpha Vantage INCOME_STATEMENT + CASH_FLOW（公司申报财报）"
    },
    "ORCL": {
      "status": "ready",
      "company": "Oracle",
      "fiscalPeriodEnd": "2026-05-31",
      "revenueTTM": 67358000000.0,
      "operatingCashflowTTM": 31977000000.0,
      "fcfTTM": -23686000000.0,
      "fcfMarginTTM": -0.3516434573473084,
      "fcfMargin3yMedian": -0.00686423108416523,
      "normalizedFcfMargin": -0.23097072815520828,
      "ttmWeight": 0.65,
      "terminalGrowth": 0.025,
      "riskFreeRate": 0.0425,
      "equityRiskPremium": 0.05,
      "impliedGrowthStatus": "unavailable",
      "impliedGrowthNote": "归一化自由现金流率为负，终值模型没有经济上有效的解。",
      "rationale": "云基础设施扩张带来较高资本开支，当前现金流率更具代表性。",
      "source": "Alpha Vantage INCOME_STATEMENT + CASH_FLOW（公司申报财报）"
    },
    "PLTR": {
      "status": "ready",
      "company": "Palantir",
      "fiscalPeriodEnd": "2026-03-31",
      "revenueTTM": 5224174000.0,
      "operatingCashflowTTM": 2722375000.0,
      "fcfTTM": 2687276000.0,
      "fcfMarginTTM": 0.5143925144912861,
      "fcfMargin3yMedian": 0.3982649492742471,
      "normalizedFcfMargin": 0.4795542449261744,
      "ttmWeight": 0.7,
      "terminalGrowth": 0.025,
      "riskFreeRate": 0.0425,
      "equityRiskPremium": 0.05,
      "rationale": "商业化规模仍在快速变化，较重视最新已披露的现金流表现。",
      "source": "Alpha Vantage INCOME_STATEMENT + CASH_FLOW（公司申报财报）"
    }
  }
}
